itunizer/__init__.py
itunizer/__main__.py
itunizer/itunizer.py
itunizer-1.0.7.dist-info/LICENSE
itunizer-1.0.7.dist-info/METADATA
itunizer-1.0.7.dist-info/WHEEL
itunizer-1.0.7.dist-info/entry_points.txt
itunizer-1.0.7.dist-info/RECORD
