Metadata-Version: 2.1
Name: itunizer
Version: 1.0.7
Summary: A command line tool to search and compare prices of apps and music on the Apple Store
Author: James Campbell
Author-email: james@jamescampbell.us
Requires-Python: >=3.11,<4.0
Classifier: Programming Language :: Python :: 3
Classifier: Programming Language :: Python :: 3.11
Classifier: Programming Language :: Python :: 3.12
Requires-Dist: argparse (>=1.4.0,<2.0.0)
Requires-Dist: certifi (>=2024.2.2,<2025.0.0)
Requires-Dist: chardet (>=5.2.0,<6.0.0)
Requires-Dist: idna (>=3.7,<4.0)
Requires-Dist: numpy (>=1.26.4,<2.0.0)
Requires-Dist: pandas (>=2.2.2,<3.0.0)
Requires-Dist: python-dateutil (>=2.9.0.post0,<3.0.0)
Requires-Dist: pytz (>=2024.1,<2025.0)
Requires-Dist: requests (>=2.31.0,<3.0.0)
Requires-Dist: six (>=1.16.0,<2.0.0)
Requires-Dist: urllib3 (>=2.2.1,<3.0.0)
